seismos_package/__init__.py
seismos_package/config.py
seismos_package/logging/__init__.py
seismos_package/logging/configuration.py
seismos_package/logging/formatter.py
seismos_package/logging/logger.py
seismos_package/logging/middlewares.py
seismos_package-0.1.9.dist-info/METADATA
seismos_package-0.1.9.dist-info/WHEEL
seismos_package-0.1.9.dist-info/RECORD
