Metadata-Version: 2.1
Name: seismos-package
Version: 0.1.9
Summary: Seismos internal Python package for structured logging and utilities.
Keywords: logging,utilities,internal-package
Author: Seismos
Requires-Python: >=3.8,<3.13
Classifier: Development Status :: 2 - Pre-Alpha
Classifier: Intended Audience :: Developers
Classifier: License :: Other/Proprietary License
Classifier: Natural Language :: English
Classifier: Programming Language :: Python :: 3
Classifier: Programming Language :: Python :: 3.8
Classifier: Programming Language :: Python :: 3.9
Classifier: Programming Language :: Python :: 3.10
Classifier: Programming Language :: Python :: 3.11
Classifier: Programming Language :: Python :: 3.12
Requires-Dist: fastapi (>=0.114.2,<0.116.0)
Requires-Dist: flask (>=2.2.0,<3.0.0)
Requires-Dist: httpx (>=0.28.1,<0.29.0)
Requires-Dist: python-json-logger (>=3.2.1,<4.0.0)
Requires-Dist: structlog (>=24.4.0,<25.0.0)
